{
    "events": [],
    "news": [
        {
            "id": 1,
            "title": "Site en maintenance",
            "date": "2025-01-01",
            "tag": "info",
            "content": "Mise à jour de la base de données en cours...",
            "image": null
        }
    ],
    "settings": {
        "orgName": "Cor-Tech",
        "themeColor": "#2563eb",
        "logoUrl": null,
        "hours": {
            "school": "Lundi: 9h-12h",
            "holidays": "Fermé"
        },
        "emailjs": {},
        "social": {}
    }
}
